earnapi/__init__.py
earnapi/client.py
earnapi/errors.py
earnapi/models.py
earnapi-1.1.2.dist-info/LICENSE
earnapi-1.1.2.dist-info/METADATA
earnapi-1.1.2.dist-info/WHEEL
earnapi-1.1.2.dist-info/top_level.txt
earnapi-1.1.2.dist-info/RECORD
