Metadata-Version: 2.1
Name: earnapi
Version: 1.1.2
Summary: Asynchronous EarnApp API wrapper written in Python using asyncio.
Home-page: https://github.com/Vinchethescript/earnapi
Author: Vinche.zsh
Author-email: 
License: GPL-3.0
Keywords: python,earnapi,python earnapp api,python earnapp api wrapper,earnapp api wrapper,earnapp,passive income,earnapp api,earnapp dashboard,requests,python earnapp
Requires-Python: >=3.7
License-File: LICENSE
Requires-Dist: aiohttp
